{
  "main": {
    "id": "d0c14cc675cac024",
    "type": "split",
    "children": [
      {
        "id": "d4f0e1428c3e0607",
        "type": "tabs",
        "children": [
          {
            "id": "f995c49a9bd8dce2",
            "type": "leaf",
            "state": {
              "type": "markdown",
              "state": {
                "file": "(Year 4) Advanced Aero Management/1 Introduction/Parameter Estimation Overview.md",
                "mode": "preview",
                "source": true
              },
              "icon": "lucide-file",
              "title": "Parameter Estimation Overview"
            }
          },
          {
            "id": "cf20a85634bda801",
            "type": "leaf",
            "state": {
              "type": "markdown",
              "state": {
                "file": "(Year 1,2) Mathematics for Engineering and the Environment/Year 1/13 Statistics 1/standard deviation for probabability functions.md",
                "mode": "preview",
                "source": true
              },
              "icon": "lucide-file",
              "title": "standard deviation for probabability functions"
            }
          }
        ]
      }
    ],
    "direction": "vertical"
  },
  "left": {
    "id": "cc1bd9a94f95c536",
    "type": "split",
    "children": [
      {
        "id": "9e274904d58ff975",
        "type": "tabs",
        "children": [
          {
            "id": "9dba8c53e0736664",
            "type": "leaf",
            "state": {
              "type": "file-explorer",
              "state": {
                "sortOrder": "alphabetical"
              },
              "icon": "lucide-folder-closed",
              "title": "Files"
            }
          },
          {
            "id": "075671ccff8c4b69",
            "type": "leaf",
            "state": {
              "type": "search",
              "state": {
                "query": "",
                "matchingCase": false,
                "explainSearch": false,
                "collapseAll": true,
                "extraContext": false,
                "sortOrder": "alphabetical"
              },
              "icon": "lucide-search",
              "title": "Search"
            }
          },
          {
            "id": "013240ac8a59389f",
            "type": "leaf",
            "state": {
              "type": "starred",
              "state": {},
              "icon": "lucide-file",
              "title": "Plugin no longer active"
            }
          },
          {
            "id": "74f6af087305b76a",
            "type": "leaf",
            "state": {
              "type": "bookmarks",
              "state": {},
              "icon": "lucide-bookmark",
              "title": "Bookmarks"
            }
          }
        ]
      }
    ],
    "direction": "horizontal",
    "width": 214.5
  },
  "right": {
    "id": "12c168c46d609ed6",
    "type": "split",
    "children": [
      {
        "id": "b6972ccb990ee134",
        "type": "tabs",
        "children": [
          {
            "id": "3d7e22d6e635444b",
            "type": "leaf",
            "state": {
              "type": "backlink",
              "state": {
                "file": "(Year 4) Advanced Aero Management/1 Introduction/Parameter Estimation Overview.md",
                "collapseAll": false,
                "extraContext": false,
                "sortOrder": "alphabetical",
                "showSearch": true,
                "searchQuery": "",
                "backlinkCollapsed": false,
                "unlinkedCollapsed": false
              },
              "icon": "links-coming-in",
              "title": "Backlinks for Parameter Estimation Overview"
            }
          },
          {
            "id": "2fba8ea68884c642",
            "type": "leaf",
            "state": {
              "type": "tag",
              "state": {
                "sortOrder": "frequency",
                "useHierarchy": true
              },
              "icon": "lucide-tags",
              "title": "Tags"
            }
          },
          {
            "id": "f129e36997eea1cb",
            "type": "leaf",
            "state": {
              "type": "advanced-tables-toolbar",
              "state": {},
              "icon": "spreadsheet",
              "title": "Advanced Tables"
            }
          }
        ]
      }
    ],
    "direction": "horizontal",
    "width": 200
  },
  "left-ribbon": {
    "hiddenItems": {
      "switcher:Open quick switcher": false,
      "graph:Open graph view": false,
      "canvas:Create new canvas": false,
      "daily-notes:Open today's daily note": false,
      "templates:Insert template": false,
      "command-palette:Open command palette": false,
      "markdown-importer:Open format converter": false,
      "templater-obsidian:Templater": false,
      "table-editor-obsidian:Advanced Tables Toolbar": false,
      "flashcards-obsidian:Generate flashcards": false
    }
  },
  "active": "f995c49a9bd8dce2",
  "lastOpenFiles": [
    "(Year 1,2) Mathematics for Engineering and the Environment/Year 1/13 Statistics 1/standard deviation for probabability functions.md",
    "(Year 4) Advanced Aero Management/1 Introduction/Parameter Estimation Overview.md",
    "(Year 4) Advanced Aero Management/Advanced Aerospace Management Navigation Page.md",
    "(Year 4) Advanced Aero Management/4 Reliability/Reliability Importance Metrics Overview.md",
    "(Year 4) Advanced Aero Management/4 Reliability/Reliability Model Advanced Components Overview.md",
    "(Year 4) Advanced Aero Management/4 Reliability/Distributing random numbers Overview.md",
    "(Year 4) Advanced Aero Management/3 Censorship/Censored Data Overview.md",
    "(Year 4) Advanced Aero Management/3 Censorship/censored maximum likelihood estimation.md",
    "(Year 4) Advanced Aero Management/1 Introduction/continuous distribution functions.md",
    "(Year 4) Advanced Aero Management/1 Introduction/hazard function.md",
    "(Year 4) Advanced Aero Management/4 Reliability/competing risk model.md",
    "(Year 4) Advanced Aero Management/4 Reliability/load-sharing systems.md",
    "(Year 4) Advanced Aero Management/4 Reliability/Load Sharing Systems Overview.md",
    "(Year 4) Advanced Aero Management/4 Reliability/Criticality importance measure.md",
    "(Year 4) Advanced Aero Management/4 Reliability/Birnbaum importance measure.md",
    "(Year 4) Advanced Aero Management/4 Reliability/complex reliability model.md",
    "(Year 4) Advanced Aero Management/1 Introduction/binomial coefficient.md",
    "(Year 4) Advanced Aero Management/1 Introduction/Continuous Variations Overview.md",
    "(Year 4) Advanced Aero Management/4 Reliability/Systems Reliability Models Overview.md",
    "(Year 4) Advanced Aero Management/2 Multivariate PDFs/Multi-variate Distributions Overview.md",
    "(Personal) Electronics stuff/6 Mechatronics/4 Robotic Sytems/Gazebo Fundamentals Overview.md",
    "(Personal) Electronics stuff/6 Mechatronics/4 Robotic Sytems/Robotic Systems Overview.md",
    "(Personal) Electronics stuff/6 Mechatronics/4 Robotic Sytems/ROS Fundamentals Overview.md",
    "(Personal) Electronics stuff/Electronics Engineer Root Page.md",
    "(Year 4) Advanced Aero Management/5 Maintenance Scheduling/Maintenance and Inspection Overview.md",
    "(Personal) Electronics stuff/6 Mechatronics/4 Robotic Sytems/ROS packages and workspaces.md",
    "images/The Lady Cirno's Impeccable Arithmetic Seminarium.mp4",
    "images/976E4384-3A87-405D-8905-947C659007E1.png",
    "images/Pasted image 20241114150138.png",
    "images/Pasted image 20241114145010.png",
    "images/Pasted image 20241114144741.png",
    "images/Pasted image 20241114133135.png",
    "(Year 4) Advanced Aero Management/5 Maintenance Scheduling",
    "(Year 4) Advanced Aero Management/Slides/Lecture_16.pdf",
    "(Year 4) Advanced Aero Management/Slides/Lecture_17.pdf",
    "(Year 4) Advanced Aero Management/Slides/Lecture_18(1).pdf",
    "(Year 4) Advanced Aero Management/Slides/Lecture_19(1).pdf",
    "(Year 4) Advanced Aero Management/Slides/Lecture_20(1).pdf",
    "(Year 4) Advanced Aero Management/Slides/Lecture_21(1).pdf",
    "(Year 4) Advanced Aero Management/Slides/Lecture_15.pdf",
    "(Year 4) FEA Solid Mechanics/Slides/Lecture_21(1).pdf",
    "images/Pasted image 20241114105939.png",
    "images/Pasted image 20241113164417.png",
    "images/Pasted image 20241113160452.png",
    "images/Pasted image 20241113154558.png",
    "images/Pasted image 20241113154214.png"
  ]
}